command_executor/__init__.py
command_executor/command.py
command_executor/exceptions.py
command_executor-0.1.0.dist-info/METADATA
command_executor-0.1.0.dist-info/RECORD
command_executor-0.1.0.dist-info/WHEEL
command_executor-0.1.0.dist-info/top_level.txt
