Metadata-Version: 2.1
Name: command-executor
Version: 0.1.0
Summary: command_executor provides some Python classes to make it easier to execute processes / commands and handling errors and output.
Home-page: https://github.com/moccu/python-command-executor
Author: Moccu GmbH & Co. KG
Author-email: info@moccu.com
License: UNKNOWN
Project-URL: Bug Reports, https://github.com/moccu/python-command-executor/issues
Project-URL: Source, https://github.com/moccu/python-command-executor
Keywords: commands shell processes
Platform: UNKNOWN
Classifier: Development Status :: 4 - Beta
Classifier: Environment :: Web Environment
Classifier: Intended Audience :: Developers
Classifier: License :: OSI Approved :: MIT License
Classifier: Programming Language :: Python :: 3
Classifier: Programming Language :: Python :: 3.6
